py_robot_template/TestLibrary.py
py_robot_template/__init__.py
py_robot_template-0.1.1.dist-info/METADATA
py_robot_template-0.1.1.dist-info/WHEEL
py_robot_template-0.1.1.dist-info/licenses/LICENSE
py_robot_template-0.1.1.dist-info/RECORD
