Metadata-Version: 2.4
Name: py-robot-template
Version: 0.1.1
Summary: Tempalte project for handling RobotFramework tests projects using python.
Project-URL: Homepage, https://github.com/MarcinMaciaszek/py-robot-template
Project-URL: Source, https://github.com/MarcinMaciaszek/py-robot-template
Project-URL: Tracker, https://github.com/MarcinMaciaszek/py-robot-template/issues
Project-URL: Changelog, https://github.com/MarcinMaciaszek/py-robot-template/releases
Project-URL: Documentation, https://github.com/MarcinMaciaszek/py-robot-template#readme
Project-URL: CI, https://github.com/MarcinMaciaszek/py-robot-template/actions
Project-URL: PyPI, https://pypi.org/project/py-robot-template/
Author-email: MarcinMaciaszek <marcin.maciaszek@gmail.com>
License-File: LICENSE
Requires-Python: >=3.11
Requires-Dist: robotframework>=7.3.2
Provides-Extra: dev
Requires-Dist: coverage; extra == 'dev'
Requires-Dist: mypy; extra == 'dev'
Requires-Dist: ruff; extra == 'dev'
